concrete_common-0.0.10-py3.9-nspkg.pth
concrete/common/__init__.py
concrete/common/file.py
concrete_common-0.0.10.dist-info/LICENSE
concrete_common-0.0.10.dist-info/METADATA
concrete_common-0.0.10.dist-info/WHEEL
concrete_common-0.0.10.dist-info/namespace_packages.txt
concrete_common-0.0.10.dist-info/top_level.txt
concrete_common-0.0.10.dist-info/RECORD
