Metadata-Version: 2.1
Name: concrete-common
Version: 0.0.10
Summary: Concrete common for the Concrete Framework
Home-page: https://zama.ai
Author: zama
Author-email: hello@zama.ai
License: UNKNOWN
Platform: UNKNOWN
Classifier: Programming Language :: Python :: 3
Classifier: License :: OSI Approved :: BSD License
Classifier: Operating System :: OS Independent
Requires-Python: >=3.8
License-File: LICENSE
